testrail_client/__init__.py
testrail_client/_testrail_client.py
testrail_client-0.1.2.dist-info/LICENSE
testrail_client-0.1.2.dist-info/METADATA
testrail_client-0.1.2.dist-info/WHEEL
testrail_client-0.1.2.dist-info/RECORD
